duskcrawler/__init__.py
duskcrawler/Daily_Horoscope
duskcrawler/POC_crawler.py
duskcrawler-0.1.0.dist-info/METADATA
duskcrawler-0.1.0.dist-info/WHEEL
duskcrawler-0.1.0.dist-info/RECORD
