Metadata-Version: 2.1
Name: duskcrawler
Version: 0.1.0
Summary: 
Author: DuskyRaven
Author-email: nkrucinskas@gmail.com
Requires-Python: >=3.11,<4.0
Classifier: Programming Language :: Python :: 3
Classifier: Programming Language :: Python :: 3.11
Classifier: Programming Language :: Python :: 3.12
Requires-Dist: beautifulsoup4 (>=4.12.2,<5.0.0)
Requires-Dist: lxml (>=4.9.3,<5.0.0)
Requires-Dist: pandas (>=2.1.4,<3.0.0)
Requires-Dist: requests (>=2.31.0,<3.0.0)
Requires-Dist: timeout-decorator (>=0.5.0,<0.6.0)
